{
  "filename": "Learn Acrobat - Export_2.pdf",
  "pages": [
    {
      "page_number": 1,
      "page_width": 612.0,
      "page_height": 792.0,
      "lines": [
        {
          "y": 85.7,
          "text": "Copy images",
          "bbox": [
            72.0,
            85.70401000976562,
            197.18643188476562,
            119.0160140991211
          ],
          "spans": [
            {
              "size": 24.0,
              "flags": 16,
              "bidi": 0,
              "char_flags": 24,
              "font": "Calibri-Bold",
              "color": 15606308,
              "alpha": 255,
              "ascender": 1.0390000343322754,
              "descender": -0.3490000069141388,
              "text": "Copy images",
              "origin": [
                72.0,
                110.6400146484375
              ],
              "bbox": [
                72.0,
                85.70401000976562,
                197.18643188476562,
                119.0160140991211
              ]
            }
          ]
        },
        {
          "y": 131.1,
          "text": "Use the Select tool to copy and paste individual images from a PDF to the clipboard, another",
          "bbox": [
            72.0,
            131.1480255126953,
            524.7130737304688,
            147.2040252685547
          ],
          "spans": [
            {
              "size": 12.0,
              "flags": 0,
              "bidi": 0,
              "char_flags": 16,
              "font": "Calibri",
              "color": 0,
              "alpha": 255,
              "ascender": 1.0260000228881836,
              "descender": -0.31200000643730164,
              "text": "Use the Select tool to copy and paste individual images from a PDF to the clipboard, another ",
              "origin": [
                72.0,
                143.46002197265625
              ],
              "bbox": [
                72.0,
                131.1480255126953,
                524.7130737304688,
                147.2040252685547
              ]
            }
          ]
        },
        {
          "y": 145.8,
          "text": "application, or a file.",
          "bbox": [
            72.0,
            145.78797912597656,
            174.37200927734375,
            161.84397888183594
          ],
          "spans": [
            {
              "size": 12.0,
              "flags": 0,
              "bidi": 0,
              "char_flags": 16,
              "font": "Calibri",
              "color": 0,
              "alpha": 255,
              "ascender": 1.0260000228881836,
              "descender": -0.31200000643730164,
              "text": "application, or a file. ",
              "origin": [
                72.0,
                158.0999755859375
              ],
              "bbox": [
                72.0,
                145.78797912597656,
                174.37200927734375,
                161.84397888183594
              ]
            }
          ]
        },
        {
          "y": 167.9,
          "text": "Open the Preferences dialog box if you cannot select an image because of overlapping text.",
          "bbox": [
            72.0,
            167.92799377441406,
            519.5506591796875,
            183.98399353027344
          ],
          "spans": [
            {
              "size": 12.0,
              "flags": 0,
              "bidi": 0,
              "char_flags": 16,
              "font": "Calibri",
              "color": 0,
              "alpha": 255,
              "ascender": 1.0260000228881836,
              "descender": -0.31200000643730164,
              "text": "Open the Preferences dialog box if you cannot select an image because of overlapping text. ",
              "origin": [
                72.0,
                180.239990234375
              ],
              "bbox": [
                72.0,
                167.92799377441406,
                519.5506591796875,
                183.98399353027344
              ]
            }
          ]
        },
        {
          "y": 182.4,
          "text": "Acrobat",
          "bbox": [
            104.03999328613281,
            182.41200256347656,
            143.5439910888672,
            199.06800842285156
          ],
          "spans": [
            {
              "size": 12.0,
              "flags": 16,
              "bidi": 0,
              "char_flags": 24,
              "font": "Calibri-Bold",
              "color": 0,
              "alpha": 255,
              "ascender": 1.0390000343322754,
              "descender": -0.3490000069141388,
              "text": "Acrobat",
              "origin": [
                104.03999328613281,
                194.8800048828125
              ],
              "bbox": [
                104.03999328613281,
                182.41200256347656,
                143.5439910888672,
                199.06800842285156
              ]
            }
          ]
        },
        {
          "y": 182.6,
          "text": "Select in the upper-left (macOS) or Menu in the upper-left (Windows), then",
          "bbox": [
            72.0,
            182.56800842285156,
            484.09185791015625,
            198.62400817871094
          ],
          "spans": [
            {
              "size": 12.0,
              "flags": 0,
              "bidi": 0,
              "char_flags": 16,
              "font": "Calibri",
              "color": 0,
              "alpha": 255,
              "ascender": 1.0260000228881836,
              "descender": -0.31200000643730164,
              "text": "Select ",
              "origin": [
                72.0,
                194.8800048828125
              ],
              "bbox": [
                72.0,
                182.56800842285156,
                104.05199432373047,
                198.62400817871094
              ]
            },
            {
              "size": 12.0,
              "flags": 0,
              "bidi": 0,
              "char_flags": 16,
              "font": "Calibri",
              "color": 0,
              "alpha": 255,
              "ascender": 1.0260000228881836,
              "descender": -0.31200000643730164,
              "text": " in the upper-left (macOS) or Menu in the upper-left (Windows), then ",
              "origin": [
                143.51998901367188,
                194.8800048828125
              ],
              "bbox": [
                143.51998901367188,
                182.56800842285156,
                484.09185791015625,
                198.62400817871094
              ]
            }
          ]
        },
        {
          "y": 197.1,
          "text": "Preferences Categories General Make Select tool select",
          "bbox": [
            103.25999450683594,
            197.05201721191406,
            531.9120483398438,
            213.70802307128906
          ],
          "spans": [
            {
              "size": 12.0,
              "flags": 16,
              "bidi": 0,
              "char_flags": 24,
              "font": "Calibri-Bold",
              "color": 0,
              "alpha": 255,
              "ascender": 1.0390000343322754,
              "descender": -0.3490000069141388,
              "text": "Preferences",
              "origin": [
                103.25999450683594,
                209.52001953125
              ],
              "bbox": [
                103.25999450683594,
                197.05201721191406,
                162.34796142578125,
                213.70802307128906
              ]
            },
            {
              "size": 12.0,
              "flags": 16,
              "bidi": 0,
              "char_flags": 24,
              "font": "Calibri-Bold",
              "color": 0,
              "alpha": 255,
              "ascender": 1.0390000343322754,
              "descender": -0.3490000069141388,
              "text": "Categories",
              "origin": [
                201.24000549316406,
                209.52001953125
              ],
              "bbox": [
                201.24000549316406,
                197.05201721191406,
                253.8468017578125,
                213.70802307128906
              ]
            },
            {
              "size": 12.0,
              "flags": 16,
              "bidi": 0,
              "char_flags": 24,
              "font": "Calibri-Bold",
              "color": 0,
              "alpha": 255,
              "ascender": 1.0390000343322754,
              "descender": -0.3490000069141388,
              "text": "General",
              "origin": [
                291.6000061035156,
                209.52001953125
              ],
              "bbox": [
                291.6000061035156,
                197.05201721191406,
                330.9119873046875,
                213.70802307128906
              ]
            },
            {
              "size": 12.0,
              "flags": 16,
              "bidi": 0,
              "char_flags": 24,
              "font": "Calibri-Bold",
              "color": 0,
              "alpha": 255,
              "ascender": 1.0390000343322754,
              "descender": -0.3490000069141388,
              "text": "Make Select tool select ",
              "origin": [
                414.0000305175781,
                209.52001953125
              ],
              "bbox": [
                414.0000305175781,
                197.05201721191406,
                531.9120483398438,
                213.70802307128906
              ]
            }
          ]
        },
        {
          "y": 197.2,
          "text": "select . Under , Select . Then select the",
          "bbox": [
            72.0,
            197.20802307128906,
            414.01202392578125,
            213.26402282714844
          ],
          "spans": [
            {
              "size": 12.0,
              "flags": 0,
              "bidi": 0,
              "char_flags": 16,
              "font": "Calibri",
              "color": 0,
              "alpha": 255,
              "ascender": 1.0260000228881836,
              "descender": -0.31200000643730164,
              "text": "select ",
              "origin": [
                72.0,
                209.52001953125
              ],
              "bbox": [
                72.0,
                197.20802307128906,
                103.2719955444336,
                213.26402282714844
              ]
            },
            {
              "size": 12.0,
              "flags": 0,
              "bidi": 0,
              "char_flags": 16,
              "font": "Calibri",
              "color": 0,
              "alpha": 255,
              "ascender": 1.0260000228881836,
              "descender": -0.31200000643730164,
              "text": ". Under ",
              "origin": [
                162.36000061035156,
                209.52001953125
              ],
              "bbox": [
                162.36000061035156,
                197.20802307128906,
                201.25201416015625,
                213.26402282714844
              ]
            },
            {
              "size": 12.0,
              "flags": 0,
              "bidi": 0,
              "char_flags": 16,
              "font": "Calibri",
              "color": 0,
              "alpha": 255,
              "ascender": 1.0260000228881836,
              "descender": -0.31200000643730164,
              "text": ", Select ",
              "origin": [
                253.8588104248047,
                209.52001953125
              ],
              "bbox": [
                253.8588104248047,
                197.20802307128906,
                291.61199951171875,
                213.26402282714844
              ]
            },
            {
              "size": 12.0,
              "flags": 0,
              "bidi": 0,
              "char_flags": 16,
              "font": "Calibri",
              "color": 0,
              "alpha": 255,
              "ascender": 1.0260000228881836,
              "descender": -0.31200000643730164,
              "text": ". Then select the ",
              "origin": [
                330.9000244140625,
                209.52001953125
              ],
              "bbox": [
                330.9000244140625,
                197.20802307128906,
                414.01202392578125,
                213.26402282714844
              ]
            }
          ]
        },
        {
          "y": 211.7,
          "text": "images before text",
          "bbox": [
            72.0,
            211.6919708251953,
            165.5039825439453,
            228.3479766845703
          ],
          "spans": [
            {
              "size": 12.0,
              "flags": 16,
              "bidi": 0,
              "char_flags": 24,
              "font": "Calibri-Bold",
              "color": 0,
              "alpha": 255,
              "ascender": 1.0390000343322754,
              "descender": -0.3490000069141388,
              "text": "images before text",
              "origin": [
                72.0,
                224.15997314453125
              ],
              "bbox": [
                72.0,
                211.6919708251953,
                165.5039825439453,
                228.3479766845703
              ]
            }
          ]
        },
        {
          "y": 211.8,
          "text": ".",
          "bbox": [
            165.47998046875,
            211.8479766845703,
            171.2519989013672,
            227.9039764404297
          ],
          "spans": [
            {
              "size": 12.0,
              "flags": 0,
              "bidi": 0,
              "char_flags": 16,
              "font": "Calibri",
              "color": 0,
              "alpha": 255,
              "ascender": 1.0260000228881836,
              "descender": -0.31200000643730164,
              "text": ". ",
              "origin": [
                165.47998046875,
                224.15997314453125
              ],
              "bbox": [
                165.47998046875,
                211.8479766845703,
                171.2519989013672,
                227.9039764404297
              ]
            }
          ]
        },
        {
          "y": 239.6,
          "text": "1. Using the Select tool , do one of the following:",
          "bbox": [
            90.0,
            239.6280059814453,
            353.052001953125,
            255.6840057373047
          ],
          "spans": [
            {
              "size": 12.0,
              "flags": 0,
              "bidi": 0,
              "char_flags": 16,
              "font": "Calibri",
              "color": 0,
              "alpha": 255,
              "ascender": 1.0260000228881836,
              "descender": -0.31200000643730164,
              "text": "1.",
              "origin": [
                90.0,
                251.94000244140625
              ],
              "bbox": [
                90.0,
                239.6280059814453,
                99.08399963378906,
                255.6840057373047
              ]
            },
            {
              "size": 12.0,
              "flags": 0,
              "bidi": 0,
              "char_flags": 16,
              "font": "Calibri",
              "color": 0,
              "alpha": 255,
              "ascender": 1.0260000228881836,
              "descender": -0.31200000643730164,
              "text": "Using the Select tool ",
              "origin": [
                108.0,
                251.94000244140625
              ],
              "bbox": [
                108.0,
                239.6280059814453,
                210.9720001220703,
                255.6840057373047
              ]
            },
            {
              "size": 12.0,
              "flags": 0,
              "bidi": 0,
              "char_flags": 16,
              "font": "Calibri",
              "color": 0,
              "alpha": 255,
              "ascender": 1.0260000228881836,
              "descender": -0.31200000643730164,
              "text": ", do one of the following: ",
              "origin": [
                227.94000244140625,
                251.94000244140625
              ],
              "bbox": [
                227.94000244140625,
                239.6280059814453,
                353.052001953125,
                255.6840057373047
              ]
            }
          ]
        },
        {
          "y": 261.8,
          "text": "To select the entire image, select the image or drag a rectangle around it.",
          "bbox": [
            144.0,
            261.76800537109375,
            504.13201904296875,
            277.8240051269531
          ],
          "spans": [
            {
              "size": 12.0,
              "flags": 0,
              "bidi": 0,
              "char_flags": 16,
              "font": "Calibri",
              "color": 0,
              "alpha": 255,
              "ascender": 1.0260000228881836,
              "descender": -0.31200000643730164,
              "text": "To select the entire image, select the image or drag a rectangle around it. ",
              "origin": [
                144.0,
                274.08001708984375
              ],
              "bbox": [
                144.0,
                261.76800537109375,
                504.13201904296875,
                277.8240051269531
              ]
            }
          ]
        },
        {
          "y": 264.0,
          "text": "•",
          "bbox": [
            126.0,
            264.0099182128906,
            130.6092071533203,
            276.284423828125
          ],
          "spans": [
            {
              "size": 10.020000457763672,
              "flags": 0,
              "bidi": 0,
              "char_flags": 16,
              "font": "SymbolMT",
              "color": 0,
              "alpha": 255,
              "ascender": 1.0049999952316284,
              "descender": -0.2199999988079071,
              "text": "•",
              "origin": [
                126.0,
                274.08001708984375
              ],
              "bbox": [
                126.0,
                264.0099182128906,
                130.6092071533203,
                276.284423828125
              ]
            }
          ]
        },
        {
          "y": 283.9,
          "text": "To select a portion of an image, hold the pointer over the image until the cross-",
          "bbox": [
            144.0,
            283.9079895019531,
            530.8919677734375,
            299.9639892578125
          ],
          "spans": [
            {
              "size": 12.0,
              "flags": 0,
              "bidi": 0,
              "char_flags": 16,
              "font": "Calibri",
              "color": 0,
              "alpha": 255,
              "ascender": 1.0260000228881836,
              "descender": -0.31200000643730164,
              "text": "To select a portion of an image, hold the pointer over the image until the cross-",
              "origin": [
                144.0,
                296.2200012207031
              ],
              "bbox": [
                144.0,
                283.9079895019531,
                530.8919677734375,
                299.9639892578125
              ]
            }
          ]
        },
        {
          "y": 286.1,
          "text": "•",
          "bbox": [
            126.0,
            286.14990234375,
            130.6092071533203,
            298.4244079589844
          ],
          "spans": [
            {
              "size": 10.020000457763672,
              "flags": 0,
              "bidi": 0,
              "char_flags": 16,
              "font": "SymbolMT",
              "color": 0,
              "alpha": 255,
              "ascender": 1.0049999952316284,
              "descender": -0.2199999988079071,
              "text": "•",
              "origin": [
                126.0,
                296.2200012207031
              ],
              "bbox": [
                126.0,
                286.14990234375,
                130.6092071533203,
                298.4244079589844
              ]
            }
          ]
        },
        {
          "y": 302.1,
          "text": "hair icon appears, and then drag a rectangle around the portion.",
          "bbox": [
            144.0,
            302.1479797363281,
            477.97198486328125,
            318.2039794921875
          ],
          "spans": [
            {
              "size": 12.0,
              "flags": 0,
              "bidi": 0,
              "char_flags": 16,
              "font": "Calibri",
              "color": 0,
              "alpha": 255,
              "ascender": 1.0260000228881836,
              "descender": -0.31200000643730164,
              "text": "hair icon ",
              "origin": [
                144.0,
                314.4599914550781
              ],
              "bbox": [
                144.0,
                302.1479797363281,
                188.89199829101562,
                318.2039794921875
              ]
            },
            {
              "size": 12.0,
              "flags": 0,
              "bidi": 0,
              "char_flags": 16,
              "font": "Calibri",
              "color": 0,
              "alpha": 255,
              "ascender": 1.0260000228881836,
              "descender": -0.31200000643730164,
              "text": " appears, and then drag a rectangle around the portion. ",
              "origin": [
                203.87998962402344,
                314.4599914550781
              ],
              "bbox": [
                203.87998962402344,
                302.1479797363281,
                477.97198486328125,
                318.2039794921875
              ]
            }
          ]
        },
        {
          "y": 336.9,
          "text": "Note:",
          "bbox": [
            108.0,
            336.9120178222656,
            135.91200256347656,
            353.5679931640625
          ],
          "spans": [
            {
              "size": 12.0,
              "flags": 16,
              "bidi": 0,
              "char_flags": 24,
              "font": "Calibri-Bold",
              "color": 0,
              "alpha": 255,
              "ascender": 1.0390000343322754,
              "descender": -0.3490000069141388,
              "text": "Note:",
              "origin": [
                108.0,
                349.3800048828125
              ],
              "bbox": [
                108.0,
                336.9120178222656,
                135.91200256347656,
                353.5679931640625
              ]
            }
          ]
        },
        {
          "y": 337.1,
          "text": "To deselect an image and start over, click outside it.",
          "bbox": [
            135.89999389648438,
            337.0679931640625,
            393.6119689941406,
            353.1239929199219
          ],
          "spans": [
            {
              "size": 12.0,
              "flags": 0,
              "bidi": 0,
              "char_flags": 16,
              "font": "Calibri",
              "color": 0,
              "alpha": 255,
              "ascender": 1.0260000228881836,
              "descender": -0.31200000643730164,
              "text": " To deselect an image and start over, click outside it. ",
              "origin": [
                135.89999389648438,
                349.3800048828125
              ],
              "bbox": [
                135.89999389648438,
                337.0679931640625,
                393.6119689941406,
                353.1239929199219
              ]
            }
          ]
        },
        {
          "y": 366.4,
          "text": "2. Right-click the image and select copy. Once done, you can paste it to a new file or a",
          "bbox": [
            90.0,
            366.4079895019531,
            516.1907958984375,
            382.4639892578125
          ],
          "spans": [
            {
              "size": 12.0,
              "flags": 0,
              "bidi": 0,
              "char_flags": 16,
              "font": "Calibri",
              "color": 0,
              "alpha": 255,
              "ascender": 1.0260000228881836,
              "descender": -0.31200000643730164,
              "text": "2.",
              "origin": [
                90.0,
                378.7200012207031
              ],
              "bbox": [
                90.0,
                366.4079895019531,
                99.08399963378906,
                382.4639892578125
              ]
            },
            {
              "size": 12.0,
              "flags": 0,
              "bidi": 0,
              "char_flags": 16,
              "font": "Calibri",
              "color": 0,
              "alpha": 255,
              "ascender": 1.0260000228881836,
              "descender": -0.31200000643730164,
              "text": "Right-click the image and select copy. Once done, you can paste it to a new file or a ",
              "origin": [
                108.0,
                378.7200012207031
              ],
              "bbox": [
                108.0,
                366.4079895019531,
                516.1907958984375,
                382.4639892578125
              ]
            }
          ]
        },
        {
          "y": 381.0,
          "text": "clipboard.",
          "bbox": [
            108.0,
            381.0479736328125,
            162.19200134277344,
            397.1039733886719
          ],
          "spans": [
            {
              "size": 12.0,
              "flags": 0,
              "bidi": 0,
              "char_flags": 16,
              "font": "Calibri",
              "color": 0,
              "alpha": 255,
              "ascender": 1.0260000228881836,
              "descender": -0.31200000643730164,
              "text": "clipboard.  ",
              "origin": [
                108.0,
                393.3599853515625
              ],
              "bbox": [
                108.0,
                381.0479736328125,
                162.19200134277344,
                397.1039733886719
              ]
            }
          ]
        }
      ]
    },
    {
      "page_number": 2,
      "page_width": 612.0,
      "page_height": 792.0,
      "lines": [
        {
          "y": 85.6,
          "text": "Export objects to separate PDF",
          "bbox": [
            72.0,
            85.64401245117188,
            376.95123291015625,
            118.95601654052734
          ],
          "spans": [
            {
              "size": 24.0,
              "flags": 16,
              "bidi": 0,
              "char_flags": 24,
              "font": "Calibri-Bold",
              "color": 15606308,
              "alpha": 255,
              "ascender": 1.0390000343322754,
              "descender": -0.3490000069141388,
              "text": "Export objects to separate PDF",
              "origin": [
                72.0,
                110.58001708984375
              ],
              "bbox": [
                72.0,
                85.64401245117188,
                376.95123291015625,
                118.95601654052734
              ]
            }
          ]
        },
        {
          "y": 131.0,
          "text": "Edit Object",
          "bbox": [
            120.77999877929688,
            130.9920196533203,
            175.7639923095703,
            147.6480255126953
          ],
          "spans": [
            {
              "size": 12.0,
              "flags": 16,
              "bidi": 0,
              "char_flags": 24,
              "font": "Calibri-Bold",
              "color": 0,
              "alpha": 255,
              "ascender": 1.0390000343322754,
              "descender": -0.3490000069141388,
              "text": "Edit Object",
              "origin": [
                120.77999877929688,
                143.46002197265625
              ],
              "bbox": [
                120.77999877929688,
                130.9920196533203,
                175.7639923095703,
                147.6480255126953
              ]
            }
          ]
        },
        {
          "y": 131.1,
          "text": "Using the tool, you can save objects into a separate PDF.",
          "bbox": [
            72.0,
            131.1480255126953,
            407.5920104980469,
            147.2040252685547
          ],
          "spans": [
            {
              "size": 12.0,
              "flags": 0,
              "bidi": 0,
              "char_flags": 16,
              "font": "Calibri",
              "color": 0,
              "alpha": 255,
              "ascender": 1.0260000228881836,
              "descender": -0.31200000643730164,
              "text": "Using the ",
              "origin": [
                72.0,
                143.46002197265625
              ],
              "bbox": [
                72.0,
                131.1480255126953,
                120.79199981689453,
                147.2040252685547
              ]
            },
            {
              "size": 12.0,
              "flags": 0,
              "bidi": 0,
              "char_flags": 16,
              "font": "Calibri",
              "color": 0,
              "alpha": 255,
              "ascender": 1.0260000228881836,
              "descender": -0.31200000643730164,
              "text": " tool, you can save objects into a separate PDF. ",
              "origin": [
                175.739990234375,
                143.46002197265625
              ],
              "bbox": [
                175.739990234375,
                131.1480255126953,
                407.5920104980469,
                147.2040252685547
              ]
            }
          ]
        },
        {
          "y": 153.1,
          "text": "All tools Use print production Edit object",
          "bbox": [
            99.12000274658203,
            153.11997985839844,
            360.2040100097656,
            169.78797912597656
          ],
          "spans": [
            {
              "size": 12.0,
              "flags": 0,
              "bidi": 0,
              "char_flags": 16,
              "font": "ArialMT",
              "color": 0,
              "alpha": 255,
              "ascender": 1.0399999618530273,
              "descender": -0.32499998807907104,
              "text": " ",
              "origin": [
                99.12000274658203,
                165.5999755859375
              ],
              "bbox": [
                99.12000274658203,
                153.11997985839844,
                102.45600128173828,
                169.49996948242188
              ]
            },
            {
              "size": 12.0,
              "flags": 16,
              "bidi": 0,
              "char_flags": 24,
              "font": "Calibri-Bold",
              "color": 0,
              "alpha": 255,
              "ascender": 1.0390000343322754,
              "descender": -0.3490000069141388,
              "text": "All tools",
              "origin": [
                140.0399932861328,
                165.5999755859375
              ],
              "bbox": [
                140.0399932861328,
                153.13197326660156,
                180.70797729492188,
                169.78797912597656
              ]
            },
            {
              "size": 12.0,
              "flags": 16,
              "bidi": 0,
              "char_flags": 24,
              "font": "Calibri-Bold",
              "color": 0,
              "alpha": 255,
              "ascender": 1.0390000343322754,
              "descender": -0.3490000069141388,
              "text": "Use print production",
              "origin": [
                192.11997985839844,
                165.5999755859375
              ],
              "bbox": [
                192.11997985839844,
                153.13197326660156,
                295.5240478515625,
                169.78797912597656
              ]
            },
            {
              "size": 12.0,
              "flags": 16,
              "bidi": 0,
              "char_flags": 24,
              "font": "Calibri-Bold",
              "color": 0,
              "alpha": 255,
              "ascender": 1.0390000343322754,
              "descender": -0.3490000069141388,
              "text": "Edit object",
              "origin": [
                306.8999938964844,
                165.5999755859375
              ],
              "bbox": [
                306.8999938964844,
                153.13197326660156,
                360.2040100097656,
                169.78797912597656
              ]
            }
          ]
        },
        {
          "y": 153.3,
          "text": "1. Select > > .",
          "bbox": [
            90.0,
            153.28797912597656,
            365.8919982910156,
            169.34397888183594
          ],
          "spans": [
            {
              "size": 12.0,
              "flags": 0,
              "bidi": 0,
              "char_flags": 16,
              "font": "Calibri",
              "color": 0,
              "alpha": 255,
              "ascender": 1.0260000228881836,
              "descender": -0.31200000643730164,
              "text": "1.",
              "origin": [
                90.0,
                165.5999755859375
              ],
              "bbox": [
                90.0,
                153.28797912597656,
                99.08399963378906,
                169.34397888183594
              ]
            },
            {
              "size": 12.0,
              "flags": 0,
              "bidi": 0,
              "char_flags": 16,
              "font": "Calibri",
              "color": 0,
              "alpha": 255,
              "ascender": 1.0260000228881836,
              "descender": -0.31200000643730164,
              "text": "Select ",
              "origin": [
                108.0,
                165.5999755859375
              ],
              "bbox": [
                108.0,
                153.28797912597656,
                140.052001953125,
                169.34397888183594
              ]
            },
            {
              "size": 12.0,
              "flags": 0,
              "bidi": 0,
              "char_flags": 16,
              "font": "Calibri",
              "color": 0,
              "alpha": 255,
              "ascender": 1.0260000228881836,
              "descender": -0.31200000643730164,
              "text": " > ",
              "origin": [
                180.71998596191406,
                165.5999755859375
              ],
              "bbox": [
                180.71998596191406,
                153.28797912597656,
                192.13198852539062,
                169.34397888183594
              ]
            },
            {
              "size": 12.0,
              "flags": 0,
              "bidi": 0,
              "char_flags": 16,
              "font": "Calibri",
              "color": 0,
              "alpha": 255,
              "ascender": 1.0260000228881836,
              "descender": -0.31200000643730164,
              "text": " > ",
              "origin": [
                295.50006103515625,
                165.5999755859375
              ],
              "bbox": [
                295.50006103515625,
                153.28797912597656,
                306.9119873046875,
                169.34397888183594
              ]
            },
            {
              "size": 12.0,
              "flags": 0,
              "bidi": 0,
              "char_flags": 16,
              "font": "Calibri",
              "color": 0,
              "alpha": 255,
              "ascender": 1.0260000228881836,
              "descender": -0.31200000643730164,
              "text": ". ",
              "origin": [
                360.17999267578125,
                165.5999755859375
              ],
              "bbox": [
                360.17999267578125,
                153.28797912597656,
                365.8919982910156,
                169.34397888183594
              ]
            }
          ]
        },
        {
          "y": 175.4,
          "text": "2. Select the object or objects.",
          "bbox": [
            90.0,
            175.42799377441406,
            246.552001953125,
            191.48399353027344
          ],
          "spans": [
            {
              "size": 12.0,
              "flags": 0,
              "bidi": 0,
              "char_flags": 16,
              "font": "Calibri",
              "color": 0,
              "alpha": 255,
              "ascender": 1.0260000228881836,
              "descender": -0.31200000643730164,
              "text": "2.",
              "origin": [
                90.0,
                187.739990234375
              ],
              "bbox": [
                90.0,
                175.42799377441406,
                99.08399963378906,
                191.48399353027344
              ]
            },
            {
              "size": 12.0,
              "flags": 0,
              "bidi": 0,
              "char_flags": 16,
              "font": "Calibri",
              "color": 0,
              "alpha": 255,
              "ascender": 1.0260000228881836,
              "descender": -0.31200000643730164,
              "text": "Select the object or objects. ",
              "origin": [
                108.0,
                187.739990234375
              ],
              "bbox": [
                108.0,
                175.42799377441406,
                246.552001953125,
                191.48399353027344
              ]
            }
          ]
        },
        {
          "y": 197.4,
          "text": "Save Selection As",
          "bbox": [
            99.12000274658203,
            197.40000915527344,
            374.2680358886719,
            214.06800842285156
          ],
          "spans": [
            {
              "size": 12.0,
              "flags": 0,
              "bidi": 0,
              "char_flags": 16,
              "font": "ArialMT",
              "color": 0,
              "alpha": 255,
              "ascender": 1.0399999618530273,
              "descender": -0.32499998807907104,
              "text": " ",
              "origin": [
                99.12000274658203,
                209.8800048828125
              ],
              "bbox": [
                99.12000274658203,
                197.40000915527344,
                102.45600128173828,
                213.77999877929688
              ]
            },
            {
              "size": 12.0,
              "flags": 16,
              "bidi": 0,
              "char_flags": 24,
              "font": "Calibri-Bold",
              "color": 0,
              "alpha": 255,
              "ascender": 1.0390000343322754,
              "descender": -0.3490000069141388,
              "text": "Save Selection As",
              "origin": [
                287.82000732421875,
                209.8800048828125
              ],
              "bbox": [
                287.82000732421875,
                197.41200256347656,
                374.2680358886719,
                214.06800842285156
              ]
            }
          ]
        },
        {
          "y": 197.6,
          "text": "3. Right-click the selection, and choose .",
          "bbox": [
            90.0,
            197.56800842285156,
            380.0520324707031,
            213.62400817871094
          ],
          "spans": [
            {
              "size": 12.0,
              "flags": 0,
              "bidi": 0,
              "char_flags": 16,
              "font": "Calibri",
              "color": 0,
              "alpha": 255,
              "ascender": 1.0260000228881836,
              "descender": -0.31200000643730164,
              "text": "3.",
              "origin": [
                90.0,
                209.8800048828125
              ],
              "bbox": [
                90.0,
                197.56800842285156,
                99.08399963378906,
                213.62400817871094
              ]
            },
            {
              "size": 12.0,
              "flags": 0,
              "bidi": 0,
              "char_flags": 16,
              "font": "Calibri",
              "color": 0,
              "alpha": 255,
              "ascender": 1.0260000228881836,
              "descender": -0.31200000643730164,
              "text": "Right-click the selection, and choose ",
              "origin": [
                108.0,
                209.8800048828125
              ],
              "bbox": [
                108.0,
                197.56800842285156,
                287.8320007324219,
                213.62400817871094
              ]
            },
            {
              "size": 12.0,
              "flags": 0,
              "bidi": 0,
              "char_flags": 16,
              "font": "Calibri",
              "color": 0,
              "alpha": 255,
              "ascender": 1.0260000228881836,
              "descender": -0.31200000643730164,
              "text": ". ",
              "origin": [
                374.280029296875,
                209.8800048828125
              ],
              "bbox": [
                374.280029296875,
                197.56800842285156,
                380.0520324707031,
                213.62400817871094
              ]
            }
          ]
        },
        {
          "y": 219.6,
          "text": "Save As",
          "bbox": [
            139.02000427246094,
            219.55201721191406,
            179.83200073242188,
            236.20802307128906
          ],
          "spans": [
            {
              "size": 12.0,
              "flags": 16,
              "bidi": 0,
              "char_flags": 24,
              "font": "Calibri-Bold",
              "color": 0,
              "alpha": 255,
              "ascender": 1.0390000343322754,
              "descender": -0.3490000069141388,
              "text": "Save As ",
              "origin": [
                139.02000427246094,
                232.02001953125
              ],
              "bbox": [
                139.02000427246094,
                219.55201721191406,
                179.83200073242188,
                236.20802307128906
              ]
            }
          ]
        },
        {
          "y": 219.7,
          "text": "4. In the dialog, specify where you want to save the file, name the file, and then",
          "bbox": [
            90.0,
            219.70802307128906,
            527.5330810546875,
            235.76402282714844
          ],
          "spans": [
            {
              "size": 12.0,
              "flags": 0,
              "bidi": 0,
              "char_flags": 16,
              "font": "Calibri",
              "color": 0,
              "alpha": 255,
              "ascender": 1.0260000228881836,
              "descender": -0.31200000643730164,
              "text": "4.",
              "origin": [
                90.0,
                232.02001953125
              ],
              "bbox": [
                90.0,
                219.70802307128906,
                99.08399963378906,
                235.76402282714844
              ]
            },
            {
              "size": 12.0,
              "flags": 0,
              "bidi": 0,
              "char_flags": 16,
              "font": "Calibri",
              "color": 0,
              "alpha": 255,
              "ascender": 1.0260000228881836,
              "descender": -0.31200000643730164,
              "text": "In the ",
              "origin": [
                108.0,
                232.02001953125
              ],
              "bbox": [
                108.0,
                219.70802307128906,
                139.03201293945312,
                235.76402282714844
              ]
            },
            {
              "size": 12.0,
              "flags": 0,
              "bidi": 0,
              "char_flags": 16,
              "font": "Calibri",
              "color": 0,
              "alpha": 255,
              "ascender": 1.0260000228881836,
              "descender": -0.31200000643730164,
              "text": "dialog, specify where you want to save the file, name the file, and then ",
              "origin": [
                179.8199920654297,
                232.02001953125
              ],
              "bbox": [
                179.8199920654297,
                219.70802307128906,
                527.5330810546875,
                235.76402282714844
              ]
            }
          ]
        },
        {
          "y": 234.2,
          "text": "Save",
          "bbox": [
            139.1999969482422,
            234.1919708251953,
            162.5159912109375,
            250.8479766845703
          ],
          "spans": [
            {
              "size": 12.0,
              "flags": 16,
              "bidi": 0,
              "char_flags": 24,
              "font": "Calibri-Bold",
              "color": 0,
              "alpha": 255,
              "ascender": 1.0390000343322754,
              "descender": -0.3490000069141388,
              "text": "Save",
              "origin": [
                139.1999969482422,
                246.65997314453125
              ],
              "bbox": [
                139.1999969482422,
                234.1919708251953,
                162.5159912109375,
                250.8479766845703
              ]
            }
          ]
        },
        {
          "y": 234.3,
          "text": "select .",
          "bbox": [
            108.0,
            234.3479766845703,
            168.2519989013672,
            250.4039764404297
          ],
          "spans": [
            {
              "size": 12.0,
              "flags": 0,
              "bidi": 0,
              "char_flags": 16,
              "font": "Calibri",
              "color": 0,
              "alpha": 255,
              "ascender": 1.0260000228881836,
              "descender": -0.31200000643730164,
              "text": "select ",
              "origin": [
                108.0,
                246.65997314453125
              ],
              "bbox": [
                108.0,
                234.3479766845703,
                139.27200317382812,
                250.4039764404297
              ]
            },
            {
              "size": 12.0,
              "flags": 0,
              "bidi": 0,
              "char_flags": 16,
              "font": "Calibri",
              "color": 0,
              "alpha": 255,
              "ascender": 1.0260000228881836,
              "descender": -0.31200000643730164,
              "text": ". ",
              "origin": [
                162.5399932861328,
                246.65997314453125
              ],
              "bbox": [
                162.5399932861328,
                234.3479766845703,
                168.2519989013672,
                250.4039764404297
              ]
            }
          ]
        }
      ]
    },
    {
      "page_number": 3,
      "page_width": 612.0,
      "page_height": 792.0,
      "lines": [
        {
          "y": 85.6,
          "text": "Take a snapshot of a page",
          "bbox": [
            72.0,
            85.64401245117188,
            326.87762451171875,
            118.95601654052734
          ],
          "spans": [
            {
              "size": 24.0,
              "flags": 16,
              "bidi": 0,
              "char_flags": 24,
              "font": "Calibri-Bold",
              "color": 15606308,
              "alpha": 255,
              "ascender": 1.0390000343322754,
              "descender": -0.3490000069141388,
              "text": "Take a snapshot of a page",
              "origin": [
                72.0,
                110.58001708984375
              ],
              "bbox": [
                72.0,
                85.64401245117188,
                326.87762451171875,
                118.95601654052734
              ]
            }
          ]
        },
        {
          "y": 131.1,
          "text": "You can use the Snapshot tool to copy all selected content (text, images, or both) to the",
          "bbox": [
            72.0,
            131.1480255126953,
            502.2118225097656,
            147.2040252685547
          ],
          "spans": [
            {
              "size": 12.0,
              "flags": 0,
              "bidi": 0,
              "char_flags": 16,
              "font": "Calibri",
              "color": 0,
              "alpha": 255,
              "ascender": 1.0260000228881836,
              "descender": -0.31200000643730164,
              "text": "You can use the Snapshot tool to copy all selected content (text, images, or both) to the ",
              "origin": [
                72.0,
                143.46002197265625
              ],
              "bbox": [
                72.0,
                131.1480255126953,
                502.2118225097656,
                147.2040252685547
              ]
            }
          ]
        },
        {
          "y": 145.8,
          "text": "clipboard or another application. Text and images are copied as an image.",
          "bbox": [
            72.0,
            145.78797912597656,
            434.4720153808594,
            161.84397888183594
          ],
          "spans": [
            {
              "size": 12.0,
              "flags": 0,
              "bidi": 0,
              "char_flags": 16,
              "font": "Calibri",
              "color": 0,
              "alpha": 255,
              "ascender": 1.0260000228881836,
              "descender": -0.31200000643730164,
              "text": "clipboard or another application. Text and images are copied as an image. ",
              "origin": [
                72.0,
                158.0999755859375
              ],
              "bbox": [
                72.0,
                145.78797912597656,
                434.4720153808594,
                161.84397888183594
              ]
            }
          ]
        },
        {
          "y": 167.9,
          "text": "You can use two methods to take a snapshot: the Select or Snapshot tools. Using the Select",
          "bbox": [
            72.0,
            167.92799377441406,
            518.951904296875,
            183.98399353027344
          ],
          "spans": [
            {
              "size": 12.0,
              "flags": 0,
              "bidi": 0,
              "char_flags": 16,
              "font": "Calibri",
              "color": 0,
              "alpha": 255,
              "ascender": 1.0260000228881836,
              "descender": -0.31200000643730164,
              "text": "You can use two methods to take a snapshot: the Select or Snapshot tools. Using the Select ",
              "origin": [
                72.0,
                180.239990234375
              ],
              "bbox": [
                72.0,
                167.92799377441406,
                518.951904296875,
                183.98399353027344
              ]
            }
          ]
        },
        {
          "y": 188.0,
          "text": "Take a Snapshot",
          "bbox": [
            309.9000244140625,
            187.9920196533203,
            391.1641540527344,
            204.6480255126953
          ],
          "spans": [
            {
              "size": 12.0,
              "flags": 16,
              "bidi": 0,
              "char_flags": 24,
              "font": "Calibri-Bold",
              "color": 0,
              "alpha": 255,
              "ascender": 1.0390000343322754,
              "descender": -0.3490000069141388,
              "text": "Take a Snapshot",
              "origin": [
                309.9000244140625,
                200.46002197265625
              ],
              "bbox": [
                309.9000244140625,
                187.9920196533203,
                391.1641540527344,
                204.6480255126953
              ]
            }
          ]
        },
        {
          "y": 188.1,
          "text": "tool , draw a rectangle, right-click, and select .",
          "bbox": [
            72.0,
            188.1480255126953,
            396.9120788574219,
            204.2040252685547
          ],
          "spans": [
            {
              "size": 12.0,
              "flags": 0,
              "bidi": 0,
              "char_flags": 16,
              "font": "Calibri",
              "color": 0,
              "alpha": 255,
              "ascender": 1.0260000228881836,
              "descender": -0.31200000643730164,
              "text": "tool ",
              "origin": [
                72.0,
                200.46002197265625
              ],
              "bbox": [
                72.0,
                188.1480255126953,
                94.09200286865234,
                204.2040252685547
              ]
            },
            {
              "size": 12.0,
              "flags": 0,
              "bidi": 0,
              "char_flags": 16,
              "font": "Calibri",
              "color": 0,
              "alpha": 255,
              "ascender": 1.0260000228881836,
              "descender": -0.31200000643730164,
              "text": ", draw a rectangle, right-click, and select ",
              "origin": [
                111.12000274658203,
                200.46002197265625
              ],
              "bbox": [
                111.12000274658203,
                188.1480255126953,
                309.9120178222656,
                204.2040252685547
              ]
            },
            {
              "size": 12.0,
              "flags": 0,
              "bidi": 0,
              "char_flags": 16,
              "font": "Calibri",
              "color": 0,
              "alpha": 255,
              "ascender": 1.0260000228881836,
              "descender": -0.31200000643730164,
              "text": ". ",
              "origin": [
                391.1401672363281,
                200.46002197265625
              ],
              "bbox": [
                391.1401672363281,
                188.1480255126953,
                396.9120788574219,
                204.2040252685547
              ]
            }
          ]
        },
        {
          "y": 210.3,
          "text": "To use the Snapshot tool, do the following:",
          "bbox": [
            72.0,
            210.28797912597656,
            284.052001953125,
            226.34397888183594
          ],
          "spans": [
            {
              "size": 12.0,
              "flags": 0,
              "bidi": 0,
              "char_flags": 16,
              "font": "Calibri",
              "color": 0,
              "alpha": 255,
              "ascender": 1.0260000228881836,
              "descender": -0.31200000643730164,
              "text": "To use the Snapshot tool, do the following: ",
              "origin": [
                72.0,
                222.5999755859375
              ],
              "bbox": [
                72.0,
                210.28797912597656,
                284.052001953125,
                226.34397888183594
              ]
            }
          ]
        },
        {
          "y": 232.4,
          "text": "1. (Windows) Select the hamburger menu in the upper left. Then select Undo, Redo &",
          "bbox": [
            90.0,
            232.42799377441406,
            522.1318969726562,
            248.48399353027344
          ],
          "spans": [
            {
              "size": 12.0,
              "flags": 0,
              "bidi": 0,
              "char_flags": 16,
              "font": "Calibri",
              "color": 0,
              "alpha": 255,
              "ascender": 1.0260000228881836,
              "descender": -0.31200000643730164,
              "text": "1.",
              "origin": [
                90.0,
                244.739990234375
              ],
              "bbox": [
                90.0,
                232.42799377441406,
                99.08399963378906,
                248.48399353027344
              ]
            },
            {
              "size": 12.0,
              "flags": 0,
              "bidi": 0,
              "char_flags": 16,
              "font": "Calibri",
              "color": 0,
              "alpha": 255,
              "ascender": 1.0260000228881836,
              "descender": -0.31200000643730164,
              "text": " (Windows) Select the hamburger menu ",
              "origin": [
                108.0,
                244.739990234375
              ],
              "bbox": [
                108.0,
                232.42799377441406,
                305.17205810546875,
                248.48399353027344
              ]
            },
            {
              "size": 12.0,
              "flags": 0,
              "bidi": 0,
              "char_flags": 16,
              "font": "Calibri",
              "color": 0,
              "alpha": 255,
              "ascender": 1.0260000228881836,
              "descender": -0.31200000643730164,
              "text": " in the upper left. Then select Undo, Redo & ",
              "origin": [
                305.3999938964844,
                244.739990234375
              ],
              "bbox": [
                305.3999938964844,
                232.42799377441406,
                522.1318969726562,
                248.48399353027344
              ]
            }
          ]
        },
        {
          "y": 247.1,
          "text": "more.",
          "bbox": [
            108.0,
            247.1280059814453,
            139.81201171875,
            263.1839904785156
          ],
          "spans": [
            {
              "size": 12.0,
              "flags": 0,
              "bidi": 0,
              "char_flags": 16,
              "font": "Calibri",
              "color": 0,
              "alpha": 255,
              "ascender": 1.0260000228881836,
              "descender": -0.31200000643730164,
              "text": "more. ",
              "origin": [
                108.0,
                259.44000244140625
              ],
              "bbox": [
                108.0,
                247.1280059814453,
                139.81201171875,
                263.1839904785156
              ]
            }
          ]
        },
        {
          "y": 269.3,
          "text": "(macOS) Select Edit in the upper left. Then select Undo, Redo and More",
          "bbox": [
            108.0,
            269.2679748535156,
            459.25201416015625,
            285.323974609375
          ],
          "spans": [
            {
              "size": 12.0,
              "flags": 0,
              "bidi": 0,
              "char_flags": 16,
              "font": "Calibri",
              "color": 0,
              "alpha": 255,
              "ascender": 1.0260000228881836,
              "descender": -0.31200000643730164,
              "text": "(macOS) Select Edit in the upper left. Then select Undo, Redo and More ",
              "origin": [
                108.0,
                281.5799865722656
              ],
              "bbox": [
                108.0,
                269.2679748535156,
                459.25201416015625,
                285.323974609375
              ]
            }
          ]
        },
        {
          "y": 291.4,
          "text": "2. Do one of the following:",
          "bbox": [
            90.0,
            291.4079895019531,
            228.49200439453125,
            307.4639892578125
          ],
          "spans": [
            {
              "size": 12.0,
              "flags": 0,
              "bidi": 0,
              "char_flags": 16,
              "font": "Calibri",
              "color": 0,
              "alpha": 255,
              "ascender": 1.0260000228881836,
              "descender": -0.31200000643730164,
              "text": "2.",
              "origin": [
                90.0,
                303.7200012207031
              ],
              "bbox": [
                90.0,
                291.4079895019531,
                99.08399963378906,
                307.4639892578125
              ]
            },
            {
              "size": 12.0,
              "flags": 0,
              "bidi": 0,
              "char_flags": 16,
              "font": "Calibri",
              "color": 0,
              "alpha": 255,
              "ascender": 1.0260000228881836,
              "descender": -0.31200000643730164,
              "text": "Do one of the following: ",
              "origin": [
                108.0,
                303.7200012207031
              ],
              "bbox": [
                108.0,
                291.4079895019531,
                228.49200439453125,
                307.4639892578125
              ]
            }
          ]
        },
        {
          "y": 334.8,
          "text": "Select anywhere on the page to capture the entire content displayed on the",
          "bbox": [
            144.0,
            334.8240051269531,
            522.6734008789062,
            349.583984375
          ],
          "spans": [
            {
              "size": 12.0,
              "flags": 4,
              "bidi": 0,
              "char_flags": 16,
              "font": "AdobeClean-Regular",
              "color": 3355443,
              "alpha": 255,
              "ascender": 0.9779999852180481,
              "descender": -0.25200000405311584,
              "text": "Select anywhere on the page to capture the entire content displayed on the ",
              "origin": [
                144.0,
                346.55999755859375
              ],
              "bbox": [
                144.0,
                334.8240051269531,
                522.6734008789062,
                349.583984375
              ]
            }
          ]
        },
        {
          "y": 336.5,
          "text": "•",
          "bbox": [
            126.0,
            336.4898986816406,
            130.6092071533203,
            348.764404296875
          ],
          "spans": [
            {
              "size": 10.020000457763672,
              "flags": 0,
              "bidi": 0,
              "char_flags": 16,
              "font": "SymbolMT",
              "color": 3355443,
              "alpha": 255,
              "ascender": 1.0049999952316284,
              "descender": -0.2199999988079071,
              "text": "•",
              "origin": [
                126.0,
                346.55999755859375
              ],
              "bbox": [
                126.0,
                336.4898986816406,
                130.6092071533203,
                348.764404296875
              ]
            }
          ]
        },
        {
          "y": 349.6,
          "text": "screen.",
          "bbox": [
            144.0,
            349.5840148925781,
            181.69200134277344,
            364.343994140625
          ],
          "spans": [
            {
              "size": 12.0,
              "flags": 4,
              "bidi": 0,
              "char_flags": 16,
              "font": "AdobeClean-Regular",
              "color": 3355443,
              "alpha": 255,
              "ascender": 0.9779999852180481,
              "descender": -0.25200000405311584,
              "text": "screen. ",
              "origin": [
                144.0,
                361.32000732421875
              ],
              "bbox": [
                144.0,
                349.5840148925781,
                181.69200134277344,
                364.343994140625
              ]
            }
          ]
        },
        {
          "y": 371.8,
          "text": "Drag a rectangle around the text or images or a combination of both.",
          "bbox": [
            144.0,
            371.843994140625,
            489.9119873046875,
            386.6039733886719
          ],
          "spans": [
            {
              "size": 12.0,
              "flags": 4,
              "bidi": 0,
              "char_flags": 16,
              "font": "AdobeClean-Regular",
              "color": 3355443,
              "alpha": 255,
              "ascender": 0.9779999852180481,
              "descender": -0.25200000405311584,
              "text": "Drag a rectangle around the text or images or a combination of both. ",
              "origin": [
                144.0,
                383.5799865722656
              ],
              "bbox": [
                144.0,
                371.843994140625,
                489.9119873046875,
                386.6039733886719
              ]
            }
          ]
        },
        {
          "y": 373.5,
          "text": "•",
          "bbox": [
            126.0,
            373.5098876953125,
            130.6092071533203,
            385.7843933105469
          ],
          "spans": [
            {
              "size": 10.020000457763672,
              "flags": 0,
              "bidi": 0,
              "char_flags": 16,
              "font": "SymbolMT",
              "color": 3355443,
              "alpha": 255,
              "ascender": 1.0049999952316284,
              "descender": -0.2199999988079071,
              "text": "•",
              "origin": [
                126.0,
                383.5799865722656
              ],
              "bbox": [
                126.0,
                373.5098876953125,
                130.6092071533203,
                385.7843933105469
              ]
            }
          ]
        },
        {
          "y": 394.1,
          "text": "Drag a rectangle within an image to copy just a portion of the image.",
          "bbox": [
            144.0,
            394.10400390625,
            487.6919860839844,
            408.8639831542969
          ],
          "spans": [
            {
              "size": 12.0,
              "flags": 4,
              "bidi": 0,
              "char_flags": 16,
              "font": "AdobeClean-Regular",
              "color": 3355443,
              "alpha": 255,
              "ascender": 0.9779999852180481,
              "descender": -0.25200000405311584,
              "text": "Drag a rectangle within an image to copy just a portion of the image. ",
              "origin": [
                144.0,
                405.8399963378906
              ],
              "bbox": [
                144.0,
                394.10400390625,
                487.6919860839844,
                408.8639831542969
              ]
            }
          ]
        },
        {
          "y": 395.8,
          "text": "•",
          "bbox": [
            126.0,
            395.7698974609375,
            130.6092071533203,
            408.0444030761719
          ],
          "spans": [
            {
              "size": 10.020000457763672,
              "flags": 0,
              "bidi": 0,
              "char_flags": 16,
              "font": "SymbolMT",
              "color": 3355443,
              "alpha": 255,
              "ascender": 1.0049999952316284,
              "descender": -0.2199999988079071,
              "text": "•",
              "origin": [
                126.0,
                405.8399963378906
              ],
              "bbox": [
                126.0,
                395.7698974609375,
                130.6092071533203,
                408.0444030761719
              ]
            }
          ]
        },
        {
          "y": 416.4,
          "text": "Colors in the selected area are inverted momentarily to highlight the selection.",
          "bbox": [
            144.0,
            416.364013671875,
            537.3720092773438,
            431.1239929199219
          ],
          "spans": [
            {
              "size": 12.0,
              "flags": 4,
              "bidi": 0,
              "char_flags": 16,
              "font": "AdobeClean-Regular",
              "color": 3355443,
              "alpha": 255,
              "ascender": 0.9779999852180481,
              "descender": -0.25200000405311584,
              "text": "Colors in the selected area are inverted momentarily to highlight the selection. ",
              "origin": [
                144.0,
                428.1000061035156
              ],
              "bbox": [
                144.0,
                416.364013671875,
                537.3720092773438,
                431.1239929199219
              ]
            }
          ]
        },
        {
          "y": 431.1,
          "text": "The selection is copied automatically to the clipboard when you release the",
          "bbox": [
            144.0,
            431.1239929199219,
            522.9121704101562,
            445.88397216796875
          ],
          "spans": [
            {
              "size": 12.0,
              "flags": 4,
              "bidi": 0,
              "char_flags": 16,
              "font": "AdobeClean-Regular",
              "color": 3355443,
              "alpha": 255,
              "ascender": 0.9779999852180481,
              "descender": -0.25200000405311584,
              "text": "The selection is copied automatically to the clipboard when you release the ",
              "origin": [
                144.0,
                442.8599853515625
              ],
              "bbox": [
                144.0,
                431.1239929199219,
                522.9121704101562,
                445.88397216796875
              ]
            }
          ]
        },
        {
          "y": 445.9,
          "text": "mouse/touchpad button. If a document is open in another application, go to",
          "bbox": [
            144.0,
            445.8840026855469,
            525.6717529296875,
            460.64398193359375
          ],
          "spans": [
            {
              "size": 12.0,
              "flags": 4,
              "bidi": 0,
              "char_flags": 16,
              "font": "AdobeClean-Regular",
              "color": 3355443,
              "alpha": 255,
              "ascender": 0.9779999852180481,
              "descender": -0.25200000405311584,
              "text": "mouse/touchpad button. If a document is open in another application, go to ",
              "origin": [
                144.0,
                457.6199951171875
              ],
              "bbox": [
                144.0,
                445.8840026855469,
                525.6717529296875,
                460.64398193359375
              ]
            }
          ]
        },
        {
          "y": 460.6,
          "text": "Paste",
          "bbox": [
            327.5400085449219,
            460.6440124511719,
            355.59600830078125,
            475.4280090332031
          ],
          "spans": [
            {
              "size": 12.0,
              "flags": 20,
              "bidi": 0,
              "char_flags": 24,
              "font": "AdobeClean-Bold",
              "color": 3355443,
              "alpha": 255,
              "ascender": 0.9879999756813049,
              "descender": -0.24400000274181366,
              "text": "Paste",
              "origin": [
                327.5400085449219,
                472.5
              ],
              "bbox": [
                327.5400085449219,
                460.6440124511719,
                355.59600830078125,
                475.4280090332031
              ]
            }
          ]
        },
        {
          "y": 460.8,
          "text": "the document, right-click, and select to paste the copied selection",
          "bbox": [
            144.0,
            460.7640075683594,
            504.3720703125,
            475.52398681640625
          ],
          "spans": [
            {
              "size": 12.0,
              "flags": 4,
              "bidi": 0,
              "char_flags": 16,
              "font": "AdobeClean-Regular",
              "color": 3355443,
              "alpha": 255,
              "ascender": 0.9779999852180481,
              "descender": -0.25200000405311584,
              "text": "the document, right-click, and select ",
              "origin": [
                144.0,
                472.5
              ],
              "bbox": [
                144.0,
                460.7640075683594,
                327.552001953125,
                475.52398681640625
              ]
            },
            {
              "size": 12.0,
              "flags": 4,
              "bidi": 0,
              "char_flags": 16,
              "font": "AdobeClean-Regular",
              "color": 3355443,
              "alpha": 255,
              "ascender": 0.9779999852180481,
              "descender": -0.25200000405311584,
              "text": " to paste the copied selection ",
              "origin": [
                355.6199951171875,
                472.5
              ],
              "bbox": [
                355.6199951171875,
                460.7640075683594,
                504.3720703125,
                475.52398681640625
              ]
            }
          ]
        },
        {
          "y": 475.5,
          "text": "directly into the target document.",
          "bbox": [
            144.0,
            475.5240173339844,
            313.9320068359375,
            490.28399658203125
          ],
          "spans": [
            {
              "size": 12.0,
              "flags": 4,
              "bidi": 0,
              "char_flags": 16,
              "font": "AdobeClean-Regular",
              "color": 3355443,
              "alpha": 255,
              "ascender": 0.9779999852180481,
              "descender": -0.25200000405311584,
              "text": "directly into the target document. ",
              "origin": [
                144.0,
                487.260009765625
              ],
              "bbox": [
                144.0,
                475.5240173339844,
                313.9320068359375,
                490.28399658203125
              ]
            }
          ]
        },
        {
          "y": 510.7,
          "text": "Note:",
          "bbox": [
            108.0,
            510.6840515136719,
            137.20802307128906,
            525.468017578125
          ],
          "spans": [
            {
              "size": 12.0,
              "flags": 20,
              "bidi": 0,
              "char_flags": 24,
              "font": "AdobeClean-Bold",
              "color": 3355443,
              "alpha": 255,
              "ascender": 0.9879999756813049,
              "descender": -0.24400000274181366,
              "text": "Note:",
              "origin": [
                108.0,
                522.5400390625
              ],
              "bbox": [
                108.0,
                510.6840515136719,
                137.20802307128906,
                525.468017578125
              ]
            }
          ]
        },
        {
          "y": 533.1,
          "text": "You can save all the images from a PDF. See Export images to another format . This",
          "bbox": [
            108.0,
            533.06396484375,
            523.991943359375,
            547.823974609375
          ],
          "spans": [
            {
              "size": 12.0,
              "flags": 4,
              "bidi": 0,
              "char_flags": 16,
              "font": "AdobeClean-Regular",
              "color": 3355443,
              "alpha": 255,
              "ascender": 0.9779999852180481,
              "descender": -0.25200000405311584,
              "text": "You can save all the images from a PDF. See ",
              "origin": [
                108.0,
                544.7999877929688
              ],
              "bbox": [
                108.0,
                533.06396484375,
                330.0119934082031,
                547.823974609375
              ]
            },
            {
              "size": 12.0,
              "flags": 4,
              "bidi": 0,
              "char_flags": 16,
              "font": "AdobeClean-Regular",
              "color": 157148,
              "alpha": 255,
              "ascender": 0.9779999852180481,
              "descender": -0.25200000405311584,
              "text": "Export images to another format",
              "origin": [
                330.0,
                544.7999877929688
              ],
              "bbox": [
                330.0,
                533.06396484375,
                492.6600341796875,
                547.823974609375
              ]
            },
            {
              "size": 12.0,
              "flags": 4,
              "bidi": 0,
              "char_flags": 16,
              "font": "AdobeClean-Regular",
              "color": 3355443,
              "alpha": 255,
              "ascender": 0.9779999852180481,
              "descender": -0.25200000405311584,
              "text": " . This ",
              "origin": [
                492.6600036621094,
                544.7999877929688
              ],
              "bbox": [
                492.6600036621094,
                533.06396484375,
                523.991943359375,
                547.823974609375
              ]
            }
          ]
        },
        {
          "y": 547.8,
          "text": "feature isn’t available in Reader.",
          "bbox": [
            108.0,
            547.823974609375,
            269.11199951171875,
            562.583984375
          ],
          "spans": [
            {
              "size": 12.0,
              "flags": 4,
              "bidi": 0,
              "char_flags": 16,
              "font": "AdobeClean-Regular",
              "color": 3355443,
              "alpha": 255,
              "ascender": 0.9779999852180481,
              "descender": -0.25200000405311584,
              "text": "feature isn’t available in Reader. ",
              "origin": [
                108.0,
                559.5599975585938
              ],
              "bbox": [
                108.0,
                547.823974609375,
                269.11199951171875,
                562.583984375
              ]
            }
          ]
        }
      ]
    }
  ]
}